<?xml version="1.0" encoding="UTF-8" standalone="yes"?>
<rfanimation version="1.2">
  <scene name="effect_ingame_skillback_txt_in_2_Default">
    <asset type="IMAGE" name="asset_effect_ingame_skillback_txt_in_1" path="effect_ingame_skillback_txt_in_1.png">
      <rect l="0" t="0" r="229" b="231" />
    </asset>
    <object name="effect_ingame_skillback_txt_in_1" ani="ani_effect_ingame_skillback_txt_in_1">
      <asset type="IMAGE" link="asset_effect_ingame_skillback_txt_in_1" />
    </object>
    <param type="RES" x="229" y="231" />
    <param type="LOOP" cnt="1" pendulum="0" />
    <anim name="ani_effect_ingame_skillback_txt_in_1">
      <frame cnt="0">
        <posx val="0" />
        <posy val="0" />
        <scalex val="1" />
        <scaley val="1" />
        <alpha val="0" />
        <rotate val="0" />
        <visible val="1" />
        <centerx val="0" />
        <centery val="0" />
      </frame>
      <frame cnt="200">
        <posx val="0" />
        <posy val="0" />
        <scalex val="1" />
        <scaley val="1" />
        <alpha val="1" />
        <rotate val="0" />
        <visible val="1" />
        <centerx val="0" />
        <centery val="0" />
      </frame>
      <frame cnt="600">
        <posx val="0" />
        <posy val="0" />
        <scalex val="1" />
        <scaley val="1" />
        <alpha val="1" />
        <rotate val="0" />
        <visible val="1" />
        <centerx val="0" />
        <centery val="0" />
      </frame>
      <frame cnt="1500">
        <posx val="0" />
        <posy val="0" />
        <scalex val="1" />
        <scaley val="1" />
        <alpha val="0" />
        <rotate val="0" />
        <visible val="1" />
        <centerx val="0" />
        <centery val="0" />
      </frame>
    </anim>
  </scene>
</rfanimation>