<refresh version="2">
	<properties>
		<property name="DPI" val="72" />
		<property name="UIAnimation" val="guild_mark_color_column_Animation.xml" />
	</properties>
	<base type="WND" subclass="" name="Wnd_guild_mark_color_colum">
		<pos x="0" y="0" />
		<rect l="0" t="0" r="32" b="32" />
		<Visible val="True" />
		<Anchor val="Top, Left" />
		<snd type="SHOW"></snd>
		<snd type="HIDE"></snd>
		<IsHitTestVisible val="True" />
		<ClipChildren val="False" />
		<child type="PICTURE" name="img_color" subclass="">
			<asset type="STATIC"></asset>
			<pos x="0" y="0" />
			<rect l="0" t="0" r="30" b="30" />
			<Visible val="True" />
			<Anchor val="None" />
			<center x="0" y="0" />
			<IsHitTestVisible val="True" />
			<ClipChildren val="False" />
		</child>
		<child type="PICTURE" name="color_slot_Sel" subclass="">
			<asset type="STATIC">color_slot_Sel.png</asset>
			<pos x="0" y="0" />
			<rect l="0" t="0" r="30" b="30" />
			<Visible val="True" />
			<Anchor val="None" />
			<center x="0" y="0" />
			<IsHitTestVisible val="True" />
			<ClipChildren val="False" />
		</child>
		<child type="PICTURE" name="icon_common_select" subclass="">
			<asset type="STATIC">icon_common_select.png</asset>
			<pos x="5" y="3" />
			<rect l="0" t="0" r="22" b="23" />
			<Visible val="True" />
			<Anchor val="None" />
			<center x="0" y="0" />
			<IsHitTestVisible val="True" />
			<ClipChildren val="False" />
		</child>
	</base>
</refresh>